utkarshpy/__init__.py
utkarshpy/cli.py
utkarshpy-0.3.15.dist-info/licenses/LICENSE
utkarshpy-0.3.15.dist-info/METADATA
utkarshpy-0.3.15.dist-info/WHEEL
utkarshpy-0.3.15.dist-info/entry_points.txt
utkarshpy-0.3.15.dist-info/top_level.txt
utkarshpy-0.3.15.dist-info/RECORD
