Metadata-Version: 2.4
Name: utkarshpy
Version: 0.3.15
Summary: CLI tool to automate Python project setup with GitHub integration and VS Code configuration
Home-page: https://github.com/utkarshg1/utkarshpy
Author: Utkarsh Gaikwad
Author-email: gaikwadujg@gmail.com
License: Apache License 2.0
Classifier: Programming Language :: Python :: 3
Classifier: License :: OSI Approved :: Apache Software License
Classifier: Operating System :: OS Independent
Requires-Python: >=3.8
License-File: LICENSE
Requires-Dist: uv
Dynamic: license-file
